GazeGenesis/__init__.py
GazeGenesis/ComputerVision/__init__.py
GazeGenesis/ComputerVision/Classification/__init__.py
GazeGenesis/ComputerVision/Classification/ConvolutionalNeuralNetwork/__init__.py
GazeGenesis/ComputerVision/Classification/ConvolutionalNeuralNetwork/model.py
GazeGenesis/ComputerVision/Classification/ConvolutionalNeuralNetwork/user.py
GazeGenesis/ComputerVision/Classification/GoogLeNet/__init__.py
GazeGenesis/ComputerVision/Classification/GoogLeNet/model.py
GazeGenesis/ComputerVision/Classification/GoogLeNet/user.py
GazeGenesis/ComputerVision/Classification/LeNet/__init__.py
GazeGenesis/ComputerVision/Classification/LeNet/model.py
GazeGenesis/ComputerVision/Classification/LeNet/user.py
GazeGenesis/ComputerVision/Classification/MultiLayerPerceptron/__init__.py
GazeGenesis/ComputerVision/Classification/MultiLayerPerceptron/model.py
GazeGenesis/ComputerVision/Classification/MultiLayerPerceptron/user.py
GazeGenesis/ComputerVision/Classification/ResNet/__init__.py
GazeGenesis/ComputerVision/Classification/ResNet/model.py
GazeGenesis/ComputerVision/Classification/ResNet/user.py
GazeGenesis/ComputerVision/Classification/VGG/__init__.py
GazeGenesis/ComputerVision/Classification/VGG/model.py
GazeGenesis/ComputerVision/Classification/VGG/user.py
GazeGenesis/ComputerVision/Classification/VisionTransformer/__init__.py
GazeGenesis/ComputerVision/Classification/VisionTransformer/model.py
GazeGenesis/ComputerVision/Classification/VisionTransformer/user.py
GazeGenesis/ComputerVision/Datasets/CIFAR10.py
GazeGenesis/ComputerVision/Datasets/CIFAR100.py
GazeGenesis/ComputerVision/Datasets/ImageNet.py
GazeGenesis/ComputerVision/Datasets/MNIST.py
GazeGenesis/ComputerVision/Datasets/__init__.py
GazeGenesis/ComputerVision/Generative/__init__.py
GazeGenesis/ComputerVision/Generative/DCGAN/__init__.py
GazeGenesis/ComputerVision/Generative/DCGAN/model.py
GazeGenesis/ComputerVision/Generative/DCGAN/user.py
GazeGenesis/ComputerVision/Generative/GAN/__init__.py
GazeGenesis-0.0.4.dist-info/METADATA
GazeGenesis-0.0.4.dist-info/WHEEL
GazeGenesis-0.0.4.dist-info/top_level.txt
GazeGenesis-0.0.4.dist-info/RECORD
